{"created":"Mon, 28 Nov 2016 16:44:00 GMT","license":"notspecified","md5":"e027e6ecb947095a956f360f6dd4dada","modified":"Mon, 28 Nov 2016 11:15:46 GMT","organisation":"Ministério do Planejamento, Desenvolvimento e Gestão - MP","raw":{"author":"Rúbia Meriguete","author_email":"rubia.meriguete@planejamento.gov.br","creator_user_id":"8032be7e-7fa4-4a60-9c54-7513301e3fd0","extras":[],"groups":[],"id":"1c0b45fb-6cdd-457d-bb2b-f11b24b8a512","isopen":false,"license_id":"notspecified","license_title":"License not specified","maintainer":"Rúbia Meriguete","maintainer_email":"rubia.meriguete@planejamento.gov.br","metadata_created":"2016-11-28T11:15:46.429742","metadata_modified":"2016-11-28T16:44:00.642503","name":"catalogo-de-software-do-sisp-2016","notes":"O objetivo do Catálogo de Software do SISP é centralizar as informações dos sistemas de informação utilizados pelo setor público, além das maiores necessidades de sistemas de informação dos Órgãos.\r\nCom essas informações será possível para a STI acompanhar a compra ou\r\ndesenvolvimento de sistemas de informação, auxiliar os órgãos integrantes do SISP na busca de soluções alternativas, no incentivo ao reuso de software, na coordenação de compras compartilhadas, no incentivo ao desenvolvimento colaborativo, e na troca de experiências entre os órgãos do SISP.\r\n","num_resources":1,"num_tags":3,"organization":{"approval_status":"approved","created":"2015-09-08T14:13:08.462246","description":"O [Ministério do Planejamento, Desenvolvimento e Gestão (MP)](http://www.planejamento.gov.br) é um órgão integrante do poder Executivo Federal, que atua na:\r\n\r\n* Formulação do planejamento estratégico nacional;\r\n* Avaliação dos impactos socioeconômicos das políticas e programas do governo federal e na elaboração de estudos especiais para a reformulação de políticas;\r\n* Realização de estudos e pesquisas para acompanhamento da conjuntura socioeconômica e gestão dos sistemas cartográficos e estatísticos nacionais;\r\n* Elaboração, acompanhamento e avaliação das leis de iniciativa do Poder Executivo federal previstas no art. 165 da Constituição;\r\n* Viabilização de novas fontes de recursos para os planos de governo;\r\n* Coordenação da gestão de parcerias público-privadas (PPP’s);\r\n* Coordenação do Programa de Aceleração do Crescimento – PAC;\r\n* Formulação de diretrizes, coordenação das negociações, acompanhamento e avaliação dos financiamentos externos de projetos públicos com organismos multilaterais e agências governamentais;\r\n* Coordenação e gestão dos sistemas de planejamento e orçamento federal, de pessoal civil, de administração de recursos da informação e informática e de serviços gerais, bem como das ações de organização e modernização administrativa do governo federal;\r\n* Formulação de diretrizes, coordenação e definição de critérios de governança corporativa das empresas estatais federais;\r\n* Administração patrimonial; e\r\n* Política e diretrizes para modernização da administração pública federal.","id":"fadff597-55a0-4619-8a81-cfecc9c0c2bb","image_url":"http://dados.gov.br/wp/wp-content/uploads/2015/10/ministerio-planejamento-t.jpg","is_organization":true,"name":"ministerio-do-planejamento-desenvolvimento-e-gestao-mp","revision_id":"6cf07ead-c3e4-4c68-b930-f1d6fd8f727e","state":"active","title":"Ministério do Planejamento, Desenvolvimento e Gestão - MP","type":"organization"},"owner_org":"fadff597-55a0-4619-8a81-cfecc9c0c2bb","private":false,"relationships_as_object":[],"relationships_as_subject":[],"resources":[{"cache_last_updated":null,"cache_url":null,"created":"2016-11-28T14:42:21.988542","datastore_active":false,"description":"Planilha consolidada.","format":"","hash":"","id":"0d49d71a-c50a-4ef1-bdd7-b825a15433e2","last_modified":null,"mimetype":null,"mimetype_inner":null,"name":"Catálogo de Software","package_id":"1c0b45fb-6cdd-457d-bb2b-f11b24b8a512","position":0,"resource_type":null,"revision_id":"7e0058c3-3b31-4e98-aaef-a3041a0d2f7b","size":null,"state":"active","url":"http://www.sisp.gov.br/ct-gcie/download/file/CatalogodeSoftwareSISP_18072016_LibreOffice.ods","url_type":null,"webstore_last_updated":null,"webstore_url":null}],"revision_id":"058bb473-a8f8-428f-aebb-0d180983e6e1","state":"active","tags":[{"display_name":"Catálogo","id":"d41ca72d-0b28-4415-8d39-c8e97b0b5ca6","name":"Catálogo","state":"active","vocabulary_id":null},{"display_name":"Sistemas","id":"70844ba4-54d4-4204-8a7e-a6308d41dda9","name":"Sistemas","state":"active","vocabulary_id":null},{"display_name":"Sotware","id":"3a4eecad-cb1b-4234-80bb-8dbe0d85a041","name":"Sotware","state":"active","vocabulary_id":null}],"title":"Catálogo de Software do SISP – 2016","type":"dataset","url":"http://www.sisp.gov.br/ct-gcie/download/file/CatalogodeSoftwareSISP_18072016_LibreOffice.ods","version":""}}