{"created":"Sat, 11 Mar 2017 14:55:01 GMT","license":null,"md5":"9ec96e675993d82e813bd293e657d98b","modified":"Tue, 03 Dec 2013 14:30:53 GMT","organisation":"Darlan Aragão Mesquita","raw":{"author":"Darlan Aragão Mesquita","author_email":"darlan.mesquita@sdh.gov.br","creator_user_id":null,"extras":[{"key":"Órgão - Esfera","value":"Federal"},{"key":"Órgão - Poder","value":"Executivo"}],"groups":[],"id":"cac75c94-f113-41de-93b6-7e0176b047fb","isopen":false,"license_id":null,"license_title":null,"maintainer":"Darlan Aragão Mesquita","maintainer_email":"darlan.mesquita@sdh.gov.br","metadata_created":"2013-12-03T14:30:53.701070","metadata_modified":"2017-03-11T14:55:01.875194","name":"municipios-com-conselho-municipal-de-seguranca-alimentar","notes":"Mapa dos municípios brasileiros que possuem Conselho Municipal de Segurança Alimentar em sua estrutura administrativa.","num_resources":1,"num_tags":1,"organization":null,"owner_org":null,"private":false,"relationships_as_object":[],"relationships_as_subject":[],"resources":[{"cache_last_updated":null,"cache_url":null,"created":"2013-12-03T12:30:53.751476","datastore_active":false,"description":"Servidor de Mapas sobre Direitos Humanos","format":"HTML","hash":"","id":"223b66c5-4e9b-45ac-93c8-df60aeab9a61","last_modified":null,"mimetype":null,"mimetype_inner":null,"name":null,"package_id":"cac75c94-f113-41de-93b6-7e0176b047fb","position":0,"resource_type":null,"revision_id":"d1aa3b64-4de6-422c-a1b1-2a553ba2f288","size":null,"state":"active","url":"http://www.sdh.gov.br","url_type":null,"webstore_last_updated":null,"webstore_url":null}],"revision_id":"d1aa3b64-4de6-422c-a1b1-2a553ba2f288","state":"active","tags":[{"display_name":"INDE","id":"06f7b020-8dbe-490b-8028-728e23e2336c","name":"INDE","state":"active","vocabulary_id":null}],"title":"Municípios com Conselho Municipal de Segurança Alimentar","type":"dataset","url":"http://www.metadados.inde.gov.br/geonetwork/srv/br/metadata.show?uuid=9c97e91c-0cce-4dc6-bba6-1b95367086d7&currTab=simple","version":null}}